dinner_time/__init__.py
dinner_time/_version.py
dinner_time/constants.py
dinner_time/recipes.py
dinner_time/util.py
dinner_time/tools/__init__.py
dinner_time/tools/get_recipes.py
dinner_time-0.1.data/data/share/aagnone/dinner_time/README.md
dinner_time-0.1.dist-info/METADATA
dinner_time-0.1.dist-info/RECORD
dinner_time-0.1.dist-info/WHEEL
dinner_time-0.1.dist-info/entry_points.txt
dinner_time-0.1.dist-info/top_level.txt
tools/__init__.py
tools/get_recipes.py
